rtl/traffic_light_controller.v
module traffic_light_controller(

    input clk,
    input rst,

    output reg [2:0] ns_light,
    output reg [2:0] ew_light

   );

    //------------------------------------------------
    // State Encoding
    //------------------------------------------------

    parameter S0 = 2'b00;
    parameter S1 = 2'b01;
    parameter S2 = 2'b10;
    parameter S3 = 2'b11;

    //------------------------------------------------
    // Internal Registers
    //------------------------------------------------

    reg [1:0] state;
    reg [3:0] timer;

    //------------------------------------------------
    // Sequential Logic
    //------------------------------------------------

    always @(posedge clk or posedge rst)
    begin

        if(rst)
        begin
            state <= S0;
            timer <= 0;
        end

        else
            begin

            timer <= timer + 1;

            case(state)

                //------------------------------------
                // S0
                //------------------------------------
                S0:
                begin
                    if(timer == 5)
                    begin
                        state <= S1;
                        timer <= 0;
                    end
                end

                //------------------------------------
                // S1
                //------------------------------------
                S1:
                begin
                    if(timer == 2)
                    begin
                        state <= S2;
                        timer <= 0;
                    end
                end

                //------------------------------------
                // S2
                //------------------------------------
                S2:
                begin
                    if(timer == 5)
                    begin
                        state <= S3;
                        timer <= 0;
                    end
                end

                //------------------------------------
                // S3
                //------------------------------------
                S3:
                begin
                    if(timer == 2)
                    begin
                        state <= S0;
                        timer <= 0;
                    end
                end

            endcase

        end

    end

    //------------------------------------------------
    // Output Logic
    //------------------------------------------------

    always @(*)
    begin

        case(state)

            //----------------------------------------
            // S0
            //----------------------------------------
            S0:
            begin
                ns_light = 3'b100;   // GREEN
                ew_light = 3'b001;   // RED
            end

            //----------------------------------------
            // S1
            //----------------------------------------
            S1:
            begin
                ns_light = 3'b010;   // YELLOW
                ew_light = 3'b001;   // RED
            end

            //----------------------------------------
            // S2
            //----------------------------------------
            S2:
            begin
                ns_light = 3'b001;   // RED
                ew_light = 3'b100;   // GREEN
            end

            //----------------------------------------
            // S3
            //----------------------------------------
            S3:
            begin
                ns_light = 3'b001;   // RED
                ew_light = 3'b010;   // YELLOW
            end

            //----------------------------------------
            // Default
            //----------------------------------------
            default:
            begin
                ns_light = 3'b001;
                ew_light = 3'b001;
            end

        endcase

    end

endmodule

tb/traffic_light_tb.v
`timescale 1ns/1ps

module traffic_light_tb;

    //-----------------------------------------
    // Testbench Signals
    //-----------------------------------------

    reg clk;
    reg rst;

    wire [2:0] ns_light;
    wire [2:0] ew_light;

    //-----------------------------------------
    // DUT Instantiation
    //-----------------------------------------

    traffic_light_controller dut (
        .clk(clk),
        .rst(rst),
        .ns_light(ns_light),
        .ew_light(ew_light)
    );

    //-----------------------------------------
    // Clock Generation
    //-----------------------------------------

    always #5 clk = ~clk;

    //-----------------------------------------
    // Test Sequence
    //-----------------------------------------

    initial
    begin

        clk = 0;
        rst = 1;

        // Hold reset
        #20;

        rst = 0;

        // Run simulation
        #300;

        $finish;

    end

    //-----------------------------------------
    // Monitor Outputs
    //-----------------------------------------

    initial
    begin
        $monitor(
            "Time=%0t | Reset=%b | NS=%b | EW=%b",
            $time,
            rst,
            ns_light,
            ew_light
        );
    end
//-----------------------------------------
// VCD Dump
//-----------------------------------------

initial
begin
    $dumpfile("sim/traffic.vcd");
    $dumpvars(0, traffic_light_tb);
end
endmodule

sim/traffic.vcd
$date
	Mon Jun 22 14:49:24 2026
$end
$version
	Icarus Verilog
$end
$timescale
	1ps
$end
$scope module traffic_light_tb $end
$var wire 3 ! ns_light [2:0] $end
$var wire 3 " ew_light [2:0] $end
$var reg 1 # clk $end
$var reg 1 $ rst $end
$scope module dut $end
$var wire 1 # clk $end
$var wire 1 $ rst $end
$var reg 3 % ew_light [2:0] $end
$var reg 3 & ns_light [2:0] $end
$var reg 2 ' state [1:0] $end
$var reg 4 ( timer [3:0] $end
$upscope $end
$upscope $end
$enddefinitions $end
#0
$dumpvars
b0 (
b0 '
b100 &
b1 %
1$
0#
b1 "
b100 !
$end
#5000
1#
#10000
0#
#15000
1#
#20000
0#
0$
#25000
b1 (
1#
#30000
0#
#35000
b10 (
1#
#40000
0#
#45000
b11 (
1#
#50000
0#
#55000
b100 (
1#
#60000
0#
#65000
b101 (
1#
#70000
0#
#75000
b10 !
b10 &
b1 '
b0 (
1#
#80000
0#
#85000
b1 (
1#
#90000
0#
#95000
b10 (
1#
#100000
0#
#105000
b100 "
b100 %
b1 !
b1 &
b10 '
b0 (
1#
#110000
0#
#115000
b1 (
1#
#120000
0#
#125000
b10 (
1#
#130000
0#
#135000
b11 (
1#
#140000
0#
#145000
b100 (
1#
#150000
0#
#155000
b101 (
1#
#160000
0#
#165000
b10 "
b10 %
b11 '
b0 (
1#
#170000
0#
#175000
b1 (
1#
#180000
0#
#185000
b10 (
1#
#190000
0#
#195000
b1 "
b1 %
b100 !
b100 &
b0 '
b0 (
1#
#200000
0#
#205000
b1 (
1#
#210000
0#
#215000
b10 (
1#
#220000
0#
#225000
b11 (
1#
#230000
0#
#235000
b100 (
1#
#240000
0#
#245000
b101 (
1#
#250000
0#
#255000
b10 !
b10 &
b1 '
b0 (
1#
#260000
0#
#265000
b1 (
1#
#270000
0#
#275000
b10 (
1#
#280000
0#
#285000
b100 "
b100 %
b1 !
b1 &
b10 '
b0 (
1#
#290000
0#
#295000
b1 (
1#
#300000
0#
#305000
b10 (
1#
#310000
0#
#315000
b11 (
1#
